aws_recommendation_a2/__init__.py
aws_recommendation_a2/cloudwatch.py
aws_recommendation_a2/cost_estimations.py
aws_recommendation_a2/dynamodb.py
aws_recommendation_a2/ebs.py
aws_recommendation_a2/ec2.py
aws_recommendation_a2/elb.py
aws_recommendation_a2/kms.py
aws_recommendation_a2/rds.py
aws_recommendation_a2/recommendation.py
aws_recommendation_a2/redshift.py
aws_recommendation_a2/s3.py
aws_recommendation_a2/truted_advisor.py
aws_recommendation_a2/utils.py
aws_recommendation_a2-0.0.14.dist-info/LICENCE
aws_recommendation_a2-0.0.14.dist-info/METADATA
aws_recommendation_a2-0.0.14.dist-info/WHEEL
aws_recommendation_a2-0.0.14.dist-info/top_level.txt
aws_recommendation_a2-0.0.14.dist-info/RECORD
